Metadata-Version: 2.4
Name: django-someauth
Version: 0.1.0
Summary: Simplified Django Allauth package with Tailwind templates.
Author: Farid Seidu
License: MIT
Project-URL: Homepage, https://github.com/Versedcamel153/SomeAuth
Keywords: django,authentication,allauth,social-login,tailwind
Classifier: Development Status :: 4 - Beta
Classifier: Framework :: Django
Classifier: Framework :: Django :: 4.2
Classifier: Framework :: Django :: 5.0
Classifier: Intended Audience :: Developers
Classifier: License :: OSI Approved :: MIT License
Classifier: Programming Language :: Python :: 3
Classifier: Programming Language :: Python :: 3.10
Classifier: Programming Language :: Python :: 3.11
Classifier: Programming Language :: Python :: 3.12
Requires-Python: >=3.10
License-File: LICENSE
Requires-Dist: django>=4.2
Requires-Dist: django-allauth>=0.63.0
Requires-Dist: django-allauth[socialaccount]
Requires-Dist: django-tailwind
Dynamic: license-file
